{"212641207087:11@s.whatsapp.net":true,"212691953970:1@s.whatsapp.net":true,"212781587057@s.whatsapp.net":true,"212770842116@s.whatsapp.net":true,"212768137955@s.whatsapp.net":true,"212765489827@s.whatsapp.net":true,"212724366741@s.whatsapp.net":true,"212723250851@s.whatsapp.net":true,"212719254207@s.whatsapp.net":true,"212717203285@s.whatsapp.net":true,"212715177452@s.whatsapp.net":true,"212712395536@s.whatsapp.net":true,"212711993062@s.whatsapp.net":true,"212711593091@s.whatsapp.net":true,"212710723716@s.whatsapp.net":true,"212710723716:16@s.whatsapp.net":true,"212710723716:17@s.whatsapp.net":true,"212709177208@s.whatsapp.net":true,"212709175651@s.whatsapp.net":true,"212704764219@s.whatsapp.net":true,"212703309735@s.whatsapp.net":true,"212688056078@s.whatsapp.net":true,"212675603093@s.whatsapp.net":true,"212675037533@s.whatsapp.net":true,"212667331322@s.whatsapp.net":true,"212657872364@s.whatsapp.net":true,"212649824546@s.whatsapp.net":true,"212644569182@s.whatsapp.net":true,"212639621872@s.whatsapp.net":true,"212638994932@s.whatsapp.net":true,"212633048075@s.whatsapp.net":true,"212622034038@s.whatsapp.net":true,"212622034038:11@s.whatsapp.net":true,"212776771646@s.whatsapp.net":true,"212644564601@s.whatsapp.net":true,"212641207087@s.whatsapp.net":true,"212639974735@s.whatsapp.net":true}