{"212671648947@s.whatsapp.net":true,"50943021420@s.whatsapp.net":true,"33757053602@s.whatsapp.net":true,"3197010291122@s.whatsapp.net":true,"249127028183@s.whatsapp.net":true,"212669195572@s.whatsapp.net":true,"201555416156@s.whatsapp.net":true,"201552770817@s.whatsapp.net":true,"201275357546@s.whatsapp.net":true,"201274894418@s.whatsapp.net":true,"201212161374@s.whatsapp.net":true,"201204187245@s.whatsapp.net":true,"201140129863@s.whatsapp.net":true,"201091753797@s.whatsapp.net":true,"201017456576@s.whatsapp.net":true,"201012994237@s.whatsapp.net":true,"201010481643@s.whatsapp.net":true}